{
  "type": "File",
  "start": 0,
  "end": 829,
  "loc": {
    "start": {
      "line": 1,
      "column": 0
    },
    "end": {
      "line": 35,
      "column": 0
    }
  },
  "program": {
    "type": "Program",
    "start": 0,
    "end": 829,
    "loc": {
      "start": {
        "line": 1,
        "column": 0
      },
      "end": {
        "line": 35,
        "column": 0
      }
    },
    "sourceType": "module",
    "body": [
      {
        "type": "ImportDeclaration",
        "start": 0,
        "end": 32,
        "loc": {
          "start": {
            "line": 1,
            "column": 0
          },
          "end": {
            "line": 1,
            "column": 32
          }
        },
        "specifiers": [
          {
            "type": "ImportSpecifier",
            "start": 9,
            "end": 16,
            "loc": {
              "start": {
                "line": 1,
                "column": 9
              },
              "end": {
                "line": 1,
                "column": 16
              }
            },
            "imported": {
              "type": "Identifier",
              "start": 9,
              "end": 16,
              "loc": {
                "start": {
                  "line": 1,
                  "column": 9
                },
                "end": {
                  "line": 1,
                  "column": 16
                },
                "identifierName": "Uniform"
              },
              "name": "Uniform"
            },
            "local": {
              "type": "Identifier",
              "start": 9,
              "end": 16,
              "loc": {
                "start": {
                  "line": 1,
                  "column": 9
                },
                "end": {
                  "line": 1,
                  "column": 16
                },
                "identifierName": "Uniform"
              },
              "name": "Uniform"
            }
          }
        ],
        "source": {
          "type": "StringLiteral",
          "start": 24,
          "end": 31,
          "loc": {
            "start": {
              "line": 1,
              "column": 24
            },
            "end": {
              "line": 1,
              "column": 31
            }
          },
          "extra": {
            "rawValue": "three",
            "raw": "\"three\""
          },
          "value": "three"
        }
      },
      {
        "type": "ImportDeclaration",
        "start": 33,
        "end": 74,
        "loc": {
          "start": {
            "line": 2,
            "column": 0
          },
          "end": {
            "line": 2,
            "column": 41
          }
        },
        "specifiers": [
          {
            "type": "ImportSpecifier",
            "start": 42,
            "end": 55,
            "loc": {
              "start": {
                "line": 2,
                "column": 9
              },
              "end": {
                "line": 2,
                "column": 22
              }
            },
            "imported": {
              "type": "Identifier",
              "start": 42,
              "end": 55,
              "loc": {
                "start": {
                  "line": 2,
                  "column": 9
                },
                "end": {
                  "line": 2,
                  "column": 22
                },
                "identifierName": "BlendFunction"
              },
              "name": "BlendFunction"
            },
            "local": {
              "type": "Identifier",
              "start": 42,
              "end": 55,
              "loc": {
                "start": {
                  "line": 2,
                  "column": 9
                },
                "end": {
                  "line": 2,
                  "column": 22
                },
                "identifierName": "BlendFunction"
              },
              "name": "BlendFunction"
            }
          }
        ],
        "source": {
          "type": "StringLiteral",
          "start": 63,
          "end": 73,
          "loc": {
            "start": {
              "line": 2,
              "column": 30
            },
            "end": {
              "line": 2,
              "column": 40
            }
          },
          "extra": {
            "rawValue": "../enums",
            "raw": "\"../enums\""
          },
          "value": "../enums"
        }
      },
      {
        "type": "ImportDeclaration",
        "start": 75,
        "end": 109,
        "loc": {
          "start": {
            "line": 3,
            "column": 0
          },
          "end": {
            "line": 3,
            "column": 34
          }
        },
        "specifiers": [
          {
            "type": "ImportSpecifier",
            "start": 84,
            "end": 90,
            "loc": {
              "start": {
                "line": 3,
                "column": 9
              },
              "end": {
                "line": 3,
                "column": 15
              }
            },
            "imported": {
              "type": "Identifier",
              "start": 84,
              "end": 90,
              "loc": {
                "start": {
                  "line": 3,
                  "column": 9
                },
                "end": {
                  "line": 3,
                  "column": 15
                },
                "identifierName": "Effect"
              },
              "name": "Effect"
            },
            "local": {
              "type": "Identifier",
              "start": 84,
              "end": 90,
              "loc": {
                "start": {
                  "line": 3,
                  "column": 9
                },
                "end": {
                  "line": 3,
                  "column": 15
                },
                "identifierName": "Effect"
              },
              "name": "Effect"
            }
          }
        ],
        "source": {
          "type": "StringLiteral",
          "start": 98,
          "end": 108,
          "loc": {
            "start": {
              "line": 3,
              "column": 23
            },
            "end": {
              "line": 3,
              "column": 33
            }
          },
          "extra": {
            "rawValue": "./Effect",
            "raw": "\"./Effect\""
          },
          "value": "./Effect"
        }
      },
      {
        "type": "ImportDeclaration",
        "start": 111,
        "end": 169,
        "loc": {
          "start": {
            "line": 5,
            "column": 0
          },
          "end": {
            "line": 5,
            "column": 58
          }
        },
        "specifiers": [
          {
            "type": "ImportDefaultSpecifier",
            "start": 118,
            "end": 132,
            "loc": {
              "start": {
                "line": 5,
                "column": 7
              },
              "end": {
                "line": 5,
                "column": 21
              }
            },
            "local": {
              "type": "Identifier",
              "start": 118,
              "end": 132,
              "loc": {
                "start": {
                  "line": 5,
                  "column": 7
                },
                "end": {
                  "line": 5,
                  "column": 21
                },
                "identifierName": "fragmentShader"
              },
              "name": "fragmentShader"
            }
          }
        ],
        "source": {
          "type": "StringLiteral",
          "start": 138,
          "end": 168,
          "loc": {
            "start": {
              "line": 5,
              "column": 27
            },
            "end": {
              "line": 5,
              "column": 57
            }
          },
          "extra": {
            "rawValue": "./glsl/gamma-correction.frag",
            "raw": "\"./glsl/gamma-correction.frag\""
          },
          "value": "./glsl/gamma-correction.frag"
        },
        "trailingComments": [
          {
            "type": "CommentBlock",
            "value": "*\n * A gamma correction effect.\n *\n * @deprecated Set WebGLRenderer.outputEncoding to sRGBEncoding instead.\n ",
            "start": 171,
            "end": 284,
            "loc": {
              "start": {
                "line": 7,
                "column": 0
              },
              "end": {
                "line": 11,
                "column": 3
              }
            }
          }
        ]
      },
      {
        "type": "ExportNamedDeclaration",
        "start": 286,
        "end": 828,
        "loc": {
          "start": {
            "line": 13,
            "column": 0
          },
          "end": {
            "line": 34,
            "column": 1
          }
        },
        "specifiers": [],
        "source": null,
        "declaration": {
          "type": "ClassDeclaration",
          "start": 293,
          "end": 828,
          "loc": {
            "start": {
              "line": 13,
              "column": 7
            },
            "end": {
              "line": 34,
              "column": 1
            }
          },
          "id": {
            "type": "Identifier",
            "start": 299,
            "end": 320,
            "loc": {
              "start": {
                "line": 13,
                "column": 13
              },
              "end": {
                "line": 13,
                "column": 34
              },
              "identifierName": "GammaCorrectionEffect"
            },
            "name": "GammaCorrectionEffect",
            "leadingComments": null
          },
          "superClass": {
            "type": "Identifier",
            "start": 329,
            "end": 335,
            "loc": {
              "start": {
                "line": 13,
                "column": 43
              },
              "end": {
                "line": 13,
                "column": 49
              },
              "identifierName": "Effect"
            },
            "name": "Effect"
          },
          "body": {
            "type": "ClassBody",
            "start": 336,
            "end": 828,
            "loc": {
              "start": {
                "line": 13,
                "column": 50
              },
              "end": {
                "line": 34,
                "column": 1
              }
            },
            "body": [
              {
                "type": "ClassMethod",
                "start": 612,
                "end": 825,
                "loc": {
                  "start": {
                    "line": 23,
                    "column": 1
                  },
                  "end": {
                    "line": 32,
                    "column": 2
                  }
                },
                "static": false,
                "computed": false,
                "key": {
                  "type": "Identifier",
                  "start": 612,
                  "end": 623,
                  "loc": {
                    "start": {
                      "line": 23,
                      "column": 1
                    },
                    "end": {
                      "line": 23,
                      "column": 12
                    },
                    "identifierName": "constructor"
                  },
                  "name": "constructor",
                  "leadingComments": null
                },
                "kind": "constructor",
                "id": null,
                "generator": false,
                "expression": false,
                "async": false,
                "params": [
                  {
                    "type": "AssignmentPattern",
                    "start": 624,
                    "end": 679,
                    "loc": {
                      "start": {
                        "line": 23,
                        "column": 13
                      },
                      "end": {
                        "line": 23,
                        "column": 68
                      }
                    },
                    "left": {
                      "type": "ObjectPattern",
                      "start": 624,
                      "end": 674,
                      "loc": {
                        "start": {
                          "line": 23,
                          "column": 13
                        },
                        "end": {
                          "line": 23,
                          "column": 63
                        }
                      },
                      "properties": [
                        {
                          "type": "ObjectProperty",
                          "start": 626,
                          "end": 659,
                          "loc": {
                            "start": {
                              "line": 23,
                              "column": 15
                            },
                            "end": {
                              "line": 23,
                              "column": 48
                            }
                          },
                          "method": false,
                          "shorthand": true,
                          "computed": false,
                          "key": {
                            "type": "Identifier",
                            "start": 626,
                            "end": 639,
                            "loc": {
                              "start": {
                                "line": 23,
                                "column": 15
                              },
                              "end": {
                                "line": 23,
                                "column": 28
                              },
                              "identifierName": "blendFunction"
                            },
                            "name": "blendFunction"
                          },
                          "value": {
                            "type": "AssignmentPattern",
                            "start": 626,
                            "end": 659,
                            "loc": {
                              "start": {
                                "line": 23,
                                "column": 15
                              },
                              "end": {
                                "line": 23,
                                "column": 48
                              }
                            },
                            "left": {
                              "type": "Identifier",
                              "start": 626,
                              "end": 639,
                              "loc": {
                                "start": {
                                  "line": 23,
                                  "column": 15
                                },
                                "end": {
                                  "line": 23,
                                  "column": 28
                                },
                                "identifierName": "blendFunction"
                              },
                              "name": "blendFunction"
                            },
                            "right": {
                              "type": "MemberExpression",
                              "start": 642,
                              "end": 659,
                              "loc": {
                                "start": {
                                  "line": 23,
                                  "column": 31
                                },
                                "end": {
                                  "line": 23,
                                  "column": 48
                                }
                              },
                              "object": {
                                "type": "Identifier",
                                "start": 642,
                                "end": 655,
                                "loc": {
                                  "start": {
                                    "line": 23,
                                    "column": 31
                                  },
                                  "end": {
                                    "line": 23,
                                    "column": 44
                                  },
                                  "identifierName": "BlendFunction"
                                },
                                "name": "BlendFunction"
                              },
                              "property": {
                                "type": "Identifier",
                                "start": 656,
                                "end": 659,
                                "loc": {
                                  "start": {
                                    "line": 23,
                                    "column": 45
                                  },
                                  "end": {
                                    "line": 23,
                                    "column": 48
                                  },
                                  "identifierName": "SRC"
                                },
                                "name": "SRC"
                              },
                              "computed": false
                            }
                          },
                          "extra": {
                            "shorthand": true
                          }
                        },
                        {
                          "type": "ObjectProperty",
                          "start": 661,
                          "end": 672,
                          "loc": {
                            "start": {
                              "line": 23,
                              "column": 50
                            },
                            "end": {
                              "line": 23,
                              "column": 61
                            }
                          },
                          "method": false,
                          "shorthand": true,
                          "computed": false,
                          "key": {
                            "type": "Identifier",
                            "start": 661,
                            "end": 666,
                            "loc": {
                              "start": {
                                "line": 23,
                                "column": 50
                              },
                              "end": {
                                "line": 23,
                                "column": 55
                              },
                              "identifierName": "gamma"
                            },
                            "name": "gamma"
                          },
                          "value": {
                            "type": "AssignmentPattern",
                            "start": 661,
                            "end": 672,
                            "loc": {
                              "start": {
                                "line": 23,
                                "column": 50
                              },
                              "end": {
                                "line": 23,
                                "column": 61
                              }
                            },
                            "left": {
                              "type": "Identifier",
                              "start": 661,
                              "end": 666,
                              "loc": {
                                "start": {
                                  "line": 23,
                                  "column": 50
                                },
                                "end": {
                                  "line": 23,
                                  "column": 55
                                },
                                "identifierName": "gamma"
                              },
                              "name": "gamma"
                            },
                            "right": {
                              "type": "NumericLiteral",
                              "start": 669,
                              "end": 672,
                              "loc": {
                                "start": {
                                  "line": 23,
                                  "column": 58
                                },
                                "end": {
                                  "line": 23,
                                  "column": 61
                                }
                              },
                              "extra": {
                                "rawValue": 2,
                                "raw": "2.0"
                              },
                              "value": 2
                            }
                          },
                          "extra": {
                            "shorthand": true
                          }
                        }
                      ]
                    },
                    "right": {
                      "type": "ObjectExpression",
                      "start": 677,
                      "end": 679,
                      "loc": {
                        "start": {
                          "line": 23,
                          "column": 66
                        },
                        "end": {
                          "line": 23,
                          "column": 68
                        }
                      },
                      "properties": []
                    }
                  }
                ],
                "body": {
                  "type": "BlockStatement",
                  "start": 681,
                  "end": 825,
                  "loc": {
                    "start": {
                      "line": 23,
                      "column": 70
                    },
                    "end": {
                      "line": 32,
                      "column": 2
                    }
                  },
                  "body": [
                    {
                      "type": "ExpressionStatement",
                      "start": 686,
                      "end": 821,
                      "loc": {
                        "start": {
                          "line": 25,
                          "column": 2
                        },
                        "end": {
                          "line": 30,
                          "column": 5
                        }
                      },
                      "expression": {
                        "type": "CallExpression",
                        "start": 686,
                        "end": 820,
                        "loc": {
                          "start": {
                            "line": 25,
                            "column": 2
                          },
                          "end": {
                            "line": 30,
                            "column": 4
                          }
                        },
                        "callee": {
                          "type": "Super",
                          "start": 686,
                          "end": 691,
                          "loc": {
                            "start": {
                              "line": 25,
                              "column": 2
                            },
                            "end": {
                              "line": 25,
                              "column": 7
                            }
                          }
                        },
                        "arguments": [
                          {
                            "type": "StringLiteral",
                            "start": 692,
                            "end": 715,
                            "loc": {
                              "start": {
                                "line": 25,
                                "column": 8
                              },
                              "end": {
                                "line": 25,
                                "column": 31
                              }
                            },
                            "extra": {
                              "rawValue": "GammaCorrectionEffect",
                              "raw": "\"GammaCorrectionEffect\""
                            },
                            "value": "GammaCorrectionEffect"
                          },
                          {
                            "type": "Identifier",
                            "start": 717,
                            "end": 731,
                            "loc": {
                              "start": {
                                "line": 25,
                                "column": 33
                              },
                              "end": {
                                "line": 25,
                                "column": 47
                              },
                              "identifierName": "fragmentShader"
                            },
                            "name": "fragmentShader"
                          },
                          {
                            "type": "ObjectExpression",
                            "start": 733,
                            "end": 819,
                            "loc": {
                              "start": {
                                "line": 25,
                                "column": 49
                              },
                              "end": {
                                "line": 30,
                                "column": 3
                              }
                            },
                            "properties": [
                              {
                                "type": "ObjectProperty",
                                "start": 738,
                                "end": 751,
                                "loc": {
                                  "start": {
                                    "line": 26,
                                    "column": 3
                                  },
                                  "end": {
                                    "line": 26,
                                    "column": 16
                                  }
                                },
                                "method": false,
                                "shorthand": true,
                                "computed": false,
                                "key": {
                                  "type": "Identifier",
                                  "start": 738,
                                  "end": 751,
                                  "loc": {
                                    "start": {
                                      "line": 26,
                                      "column": 3
                                    },
                                    "end": {
                                      "line": 26,
                                      "column": 16
                                    },
                                    "identifierName": "blendFunction"
                                  },
                                  "name": "blendFunction"
                                },
                                "value": {
                                  "type": "Identifier",
                                  "start": 738,
                                  "end": 751,
                                  "loc": {
                                    "start": {
                                      "line": 26,
                                      "column": 3
                                    },
                                    "end": {
                                      "line": 26,
                                      "column": 16
                                    },
                                    "identifierName": "blendFunction"
                                  },
                                  "name": "blendFunction"
                                },
                                "extra": {
                                  "shorthand": true
                                }
                              },
                              {
                                "type": "ObjectProperty",
                                "start": 756,
                                "end": 815,
                                "loc": {
                                  "start": {
                                    "line": 27,
                                    "column": 3
                                  },
                                  "end": {
                                    "line": 29,
                                    "column": 5
                                  }
                                },
                                "method": false,
                                "shorthand": false,
                                "computed": false,
                                "key": {
                                  "type": "Identifier",
                                  "start": 756,
                                  "end": 764,
                                  "loc": {
                                    "start": {
                                      "line": 27,
                                      "column": 3
                                    },
                                    "end": {
                                      "line": 27,
                                      "column": 11
                                    },
                                    "identifierName": "uniforms"
                                  },
                                  "name": "uniforms"
                                },
                                "value": {
                                  "type": "NewExpression",
                                  "start": 766,
                                  "end": 815,
                                  "loc": {
                                    "start": {
                                      "line": 27,
                                      "column": 13
                                    },
                                    "end": {
                                      "line": 29,
                                      "column": 5
                                    }
                                  },
                                  "callee": {
                                    "type": "Identifier",
                                    "start": 770,
                                    "end": 773,
                                    "loc": {
                                      "start": {
                                        "line": 27,
                                        "column": 17
                                      },
                                      "end": {
                                        "line": 27,
                                        "column": 20
                                      },
                                      "identifierName": "Map"
                                    },
                                    "name": "Map"
                                  },
                                  "arguments": [
                                    {
                                      "type": "ArrayExpression",
                                      "start": 774,
                                      "end": 814,
                                      "loc": {
                                        "start": {
                                          "line": 27,
                                          "column": 21
                                        },
                                        "end": {
                                          "line": 29,
                                          "column": 4
                                        }
                                      },
                                      "elements": [
                                        {
                                          "type": "ArrayExpression",
                                          "start": 780,
                                          "end": 809,
                                          "loc": {
                                            "start": {
                                              "line": 28,
                                              "column": 4
                                            },
                                            "end": {
                                              "line": 28,
                                              "column": 33
                                            }
                                          },
                                          "elements": [
                                            {
                                              "type": "StringLiteral",
                                              "start": 781,
                                              "end": 788,
                                              "loc": {
                                                "start": {
                                                  "line": 28,
                                                  "column": 5
                                                },
                                                "end": {
                                                  "line": 28,
                                                  "column": 12
                                                }
                                              },
                                              "extra": {
                                                "rawValue": "gamma",
                                                "raw": "\"gamma\""
                                              },
                                              "value": "gamma"
                                            },
                                            {
                                              "type": "NewExpression",
                                              "start": 790,
                                              "end": 808,
                                              "loc": {
                                                "start": {
                                                  "line": 28,
                                                  "column": 14
                                                },
                                                "end": {
                                                  "line": 28,
                                                  "column": 32
                                                }
                                              },
                                              "callee": {
                                                "type": "Identifier",
                                                "start": 794,
                                                "end": 801,
                                                "loc": {
                                                  "start": {
                                                    "line": 28,
                                                    "column": 18
                                                  },
                                                  "end": {
                                                    "line": 28,
                                                    "column": 25
                                                  },
                                                  "identifierName": "Uniform"
                                                },
                                                "name": "Uniform"
                                              },
                                              "arguments": [
                                                {
                                                  "type": "Identifier",
                                                  "start": 802,
                                                  "end": 807,
                                                  "loc": {
                                                    "start": {
                                                      "line": 28,
                                                      "column": 26
                                                    },
                                                    "end": {
                                                      "line": 28,
                                                      "column": 31
                                                    },
                                                    "identifierName": "gamma"
                                                  },
                                                  "name": "gamma"
                                                }
                                              ]
                                            }
                                          ]
                                        }
                                      ]
                                    }
                                  ]
                                }
                              }
                            ]
                          }
                        ]
                      }
                    }
                  ],
                  "directives": []
                },
                "leadingComments": [
                  {
                    "type": "CommentBlock",
                    "value": "*\n\t * Constructs a new gamma correction effect.\n\t *\n\t * @param {Object} [options] - The options.\n\t * @param {BlendFunction} [options.blendFunction=BlendFunction.SRC] - The blend function of this effect.\n\t * @param {Number} [options.gamma=2.0] - The gamma factor.\n\t ",
                    "start": 340,
                    "end": 609,
                    "loc": {
                      "start": {
                        "line": 15,
                        "column": 1
                      },
                      "end": {
                        "line": 21,
                        "column": 4
                      }
                    }
                  }
                ]
              }
            ]
          },
          "leadingComments": [
            {
              "type": "CommentBlock",
              "value": "*\n * A gamma correction effect.\n *\n * @deprecated Set WebGLRenderer.outputEncoding to sRGBEncoding instead.\n ",
              "start": 171,
              "end": 284,
              "loc": {
                "start": {
                  "line": 7,
                  "column": 0
                },
                "end": {
                  "line": 11,
                  "column": 3
                }
              }
            }
          ],
          "trailingComments": []
        },
        "leadingComments": [
          {
            "type": "CommentBlock",
            "value": "*\n * A gamma correction effect.\n *\n * @deprecated Set WebGLRenderer.outputEncoding to sRGBEncoding instead.\n ",
            "start": 171,
            "end": 284,
            "loc": {
              "start": {
                "line": 7,
                "column": 0
              },
              "end": {
                "line": 11,
                "column": 3
              }
            }
          }
        ]
      }
    ],
    "directives": []
  },
  "comments": [
    {
      "type": "CommentBlock",
      "value": "*\n * A gamma correction effect.\n *\n * @deprecated Set WebGLRenderer.outputEncoding to sRGBEncoding instead.\n ",
      "start": 171,
      "end": 284,
      "loc": {
        "start": {
          "line": 7,
          "column": 0
        },
        "end": {
          "line": 11,
          "column": 3
        }
      }
    },
    {
      "type": "CommentBlock",
      "value": "*\n\t * Constructs a new gamma correction effect.\n\t *\n\t * @param {Object} [options] - The options.\n\t * @param {BlendFunction} [options.blendFunction=BlendFunction.SRC] - The blend function of this effect.\n\t * @param {Number} [options.gamma=2.0] - The gamma factor.\n\t ",
      "start": 340,
      "end": 609,
      "loc": {
        "start": {
          "line": 15,
          "column": 1
        },
        "end": {
          "line": 21,
          "column": 4
        }
      }
    }
  ],
  "tokens": [
    {
      "type": {
        "label": "import",
        "keyword": "import",
        "beforeExpr": false,
        "startsExpr": true,
        "rightAssociative": false,
        "isLoop": false,
        "isAssign": false,
        "prefix": false,
        "postfix": false,
        "binop": null,
        "updateContext": null
      },
      "value": "import",
      "start": 0,
      "end": 6,
      "loc": {
        "start": {
          "line": 1,
          "column": 0
        },
        "end": {
          "line": 1,
          "column": 6
        }
      }
    },
    {
      "type": {
        "label": "{",
        "beforeExpr": true,
        "startsExpr": true,
        "rightAssociative": false,
        "isLoop": false,
        "isAssign": false,
        "prefix": false,
        "postfix": false,
        "binop": null
      },
      "start": 7,
      "end": 8,
      "loc": {
        "start": {
          "line": 1,
          "column": 7
        },
        "end": {
          "line": 1,
          "column": 8
        }
      }
    },
    {
      "type": {
        "label": "name",
        "beforeExpr": false,
        "startsExpr": true,
        "rightAssociative": false,
        "isLoop": false,
        "isAssign": false,
        "prefix": false,
        "postfix": false,
        "binop": null
      },
      "value": "Uniform",
      "start": 9,
      "end": 16,
      "loc": {
        "start": {
          "line": 1,
          "column": 9
        },
        "end": {
          "line": 1,
          "column": 16
        }
      }
    },
    {
      "type": {
        "label": "}",
        "beforeExpr": false,
        "startsExpr": false,
        "rightAssociative": false,
        "isLoop": false,
        "isAssign": false,
        "prefix": false,
        "postfix": false,
        "binop": null
      },
      "start": 17,
      "end": 18,
      "loc": {
        "start": {
          "line": 1,
          "column": 17
        },
        "end": {
          "line": 1,
          "column": 18
        }
      }
    },
    {
      "type": {
        "label": "name",
        "beforeExpr": false,
        "startsExpr": true,
        "rightAssociative": false,
        "isLoop": false,
        "isAssign": false,
        "prefix": false,
        "postfix": false,
        "binop": null
      },
      "value": "from",
      "start": 19,
      "end": 23,
      "loc": {
        "start": {
          "line": 1,
          "column": 19
        },
        "end": {
          "line": 1,
          "column": 23
        }
      }
    },
    {
      "type": {
        "label": "string",
        "beforeExpr": false,
        "startsExpr": true,
        "rightAssociative": false,
        "isLoop": false,
        "isAssign": false,
        "prefix": false,
        "postfix": false,
        "binop": null,
        "updateContext": null
      },
      "value": "three",
      "start": 24,
      "end": 31,
      "loc": {
        "start": {
          "line": 1,
          "column": 24
        },
        "end": {
          "line": 1,
          "column": 31
        }
      }
    },
    {
      "type": {
        "label": ";",
        "beforeExpr": true,
        "startsExpr": false,
        "rightAssociative": false,
        "isLoop": false,
        "isAssign": false,
        "prefix": false,
        "postfix": false,
        "binop": null,
        "updateContext": null
      },
      "start": 31,
      "end": 32,
      "loc": {
        "start": {
          "line": 1,
          "column": 31
        },
        "end": {
          "line": 1,
          "column": 32
        }
      }
    },
    {
      "type": {
        "label": "import",
        "keyword": "import",
        "beforeExpr": false,
        "startsExpr": true,
        "rightAssociative": false,
        "isLoop": false,
        "isAssign": false,
        "prefix": false,
        "postfix": false,
        "binop": null,
        "updateContext": null
      },
      "value": "import",
      "start": 33,
      "end": 39,
      "loc": {
        "start": {
          "line": 2,
          "column": 0
        },
        "end": {
          "line": 2,
          "column": 6
        }
      }
    },
    {
      "type": {
        "label": "{",
        "beforeExpr": true,
        "startsExpr": true,
        "rightAssociative": false,
        "isLoop": false,
        "isAssign": false,
        "prefix": false,
        "postfix": false,
        "binop": null
      },
      "start": 40,
      "end": 41,
      "loc": {
        "start": {
          "line": 2,
          "column": 7
        },
        "end": {
          "line": 2,
          "column": 8
        }
      }
    },
    {
      "type": {
        "label": "name",
        "beforeExpr": false,
        "startsExpr": true,
        "rightAssociative": false,
        "isLoop": false,
        "isAssign": false,
        "prefix": false,
        "postfix": false,
        "binop": null
      },
      "value": "BlendFunction",
      "start": 42,
      "end": 55,
      "loc": {
        "start": {
          "line": 2,
          "column": 9
        },
        "end": {
          "line": 2,
          "column": 22
        }
      }
    },
    {
      "type": {
        "label": "}",
        "beforeExpr": false,
        "startsExpr": false,
        "rightAssociative": false,
        "isLoop": false,
        "isAssign": false,
        "prefix": false,
        "postfix": false,
        "binop": null
      },
      "start": 56,
      "end": 57,
      "loc": {
        "start": {
          "line": 2,
          "column": 23
        },
        "end": {
          "line": 2,
          "column": 24
        }
      }
    },
    {
      "type": {
        "label": "name",
        "beforeExpr": false,
        "startsExpr": true,
        "rightAssociative": false,
        "isLoop": false,
        "isAssign": false,
        "prefix": false,
        "postfix": false,
        "binop": null
      },
      "value": "from",
      "start": 58,
      "end": 62,
      "loc": {
        "start": {
          "line": 2,
          "column": 25
        },
        "end": {
          "line": 2,
          "column": 29
        }
      }
    },
    {
      "type": {
        "label": "string",
        "beforeExpr": false,
        "startsExpr": true,
        "rightAssociative": false,
        "isLoop": false,
        "isAssign": false,
        "prefix": false,
        "postfix": false,
        "binop": null,
        "updateContext": null
      },
      "value": "../enums",
      "start": 63,
      "end": 73,
      "loc": {
        "start": {
          "line": 2,
          "column": 30
        },
        "end": {
          "line": 2,
          "column": 40
        }
      }
    },
    {
      "type": {
        "label": ";",
        "beforeExpr": true,
        "startsExpr": false,
        "rightAssociative": false,
        "isLoop": false,
        "isAssign": false,
        "prefix": false,
        "postfix": false,
        "binop": null,
        "updateContext": null
      },
      "start": 73,
      "end": 74,
      "loc": {
        "start": {
          "line": 2,
          "column": 40
        },
        "end": {
          "line": 2,
          "column": 41
        }
      }
    },
    {
      "type": {
        "label": "import",
        "keyword": "import",
        "beforeExpr": false,
        "startsExpr": true,
        "rightAssociative": false,
        "isLoop": false,
        "isAssign": false,
        "prefix": false,
        "postfix": false,
        "binop": null,
        "updateContext": null
      },
      "value": "import",
      "start": 75,
      "end": 81,
      "loc": {
        "start": {
          "line": 3,
          "column": 0
        },
        "end": {
          "line": 3,
          "column": 6
        }
      }
    },
    {
      "type": {
        "label": "{",
        "beforeExpr": true,
        "startsExpr": true,
        "rightAssociative": false,
        "isLoop": false,
        "isAssign": false,
        "prefix": false,
        "postfix": false,
        "binop": null
      },
      "start": 82,
      "end": 83,
      "loc": {
        "start": {
          "line": 3,
          "column": 7
        },
        "end": {
          "line": 3,
          "column": 8
        }
      }
    },
    {
      "type": {
        "label": "name",
        "beforeExpr": false,
        "startsExpr": true,
        "rightAssociative": false,
        "isLoop": false,
        "isAssign": false,
        "prefix": false,
        "postfix": false,
        "binop": null
      },
      "value": "Effect",
      "start": 84,
      "end": 90,
      "loc": {
        "start": {
          "line": 3,
          "column": 9
        },
        "end": {
          "line": 3,
          "column": 15
        }
      }
    },
    {
      "type": {
        "label": "}",
        "beforeExpr": false,
        "startsExpr": false,
        "rightAssociative": false,
        "isLoop": false,
        "isAssign": false,
        "prefix": false,
        "postfix": false,
        "binop": null
      },
      "start": 91,
      "end": 92,
      "loc": {
        "start": {
          "line": 3,
          "column": 16
        },
        "end": {
          "line": 3,
          "column": 17
        }
      }
    },
    {
      "type": {
        "label": "name",
        "beforeExpr": false,
        "startsExpr": true,
        "rightAssociative": false,
        "isLoop": false,
        "isAssign": false,
        "prefix": false,
        "postfix": false,
        "binop": null
      },
      "value": "from",
      "start": 93,
      "end": 97,
      "loc": {
        "start": {
          "line": 3,
          "column": 18
        },
        "end": {
          "line": 3,
          "column": 22
        }
      }
    },
    {
      "type": {
        "label": "string",
        "beforeExpr": false,
        "startsExpr": true,
        "rightAssociative": false,
        "isLoop": false,
        "isAssign": false,
        "prefix": false,
        "postfix": false,
        "binop": null,
        "updateContext": null
      },
      "value": "./Effect",
      "start": 98,
      "end": 108,
      "loc": {
        "start": {
          "line": 3,
          "column": 23
        },
        "end": {
          "line": 3,
          "column": 33
        }
      }
    },
    {
      "type": {
        "label": ";",
        "beforeExpr": true,
        "startsExpr": false,
        "rightAssociative": false,
        "isLoop": false,
        "isAssign": false,
        "prefix": false,
        "postfix": false,
        "binop": null,
        "updateContext": null
      },
      "start": 108,
      "end": 109,
      "loc": {
        "start": {
          "line": 3,
          "column": 33
        },
        "end": {
          "line": 3,
          "column": 34
        }
      }
    },
    {
      "type": {
        "label": "import",
        "keyword": "import",
        "beforeExpr": false,
        "startsExpr": true,
        "rightAssociative": false,
        "isLoop": false,
        "isAssign": false,
        "prefix": false,
        "postfix": false,
        "binop": null,
        "updateContext": null
      },
      "value": "import",
      "start": 111,
      "end": 117,
      "loc": {
        "start": {
          "line": 5,
          "column": 0
        },
        "end": {
          "line": 5,
          "column": 6
        }
      }
    },
    {
      "type": {
        "label": "name",
        "beforeExpr": false,
        "startsExpr": true,
        "rightAssociative": false,
        "isLoop": false,
        "isAssign": false,
        "prefix": false,
        "postfix": false,
        "binop": null
      },
      "value": "fragmentShader",
      "start": 118,
      "end": 132,
      "loc": {
        "start": {
          "line": 5,
          "column": 7
        },
        "end": {
          "line": 5,
          "column": 21
        }
      }
    },
    {
      "type": {
        "label": "name",
        "beforeExpr": false,
        "startsExpr": true,
        "rightAssociative": false,
        "isLoop": false,
        "isAssign": false,
        "prefix": false,
        "postfix": false,
        "binop": null
      },
      "value": "from",
      "start": 133,
      "end": 137,
      "loc": {
        "start": {
          "line": 5,
          "column": 22
        },
        "end": {
          "line": 5,
          "column": 26
        }
      }
    },
    {
      "type": {
        "label": "string",
        "beforeExpr": false,
        "startsExpr": true,
        "rightAssociative": false,
        "isLoop": false,
        "isAssign": false,
        "prefix": false,
        "postfix": false,
        "binop": null,
        "updateContext": null
      },
      "value": "./glsl/gamma-correction.frag",
      "start": 138,
      "end": 168,
      "loc": {
        "start": {
          "line": 5,
          "column": 27
        },
        "end": {
          "line": 5,
          "column": 57
        }
      }
    },
    {
      "type": {
        "label": ";",
        "beforeExpr": true,
        "startsExpr": false,
        "rightAssociative": false,
        "isLoop": false,
        "isAssign": false,
        "prefix": false,
        "postfix": false,
        "binop": null,
        "updateContext": null
      },
      "start": 168,
      "end": 169,
      "loc": {
        "start": {
          "line": 5,
          "column": 57
        },
        "end": {
          "line": 5,
          "column": 58
        }
      }
    },
    {
      "type": "CommentBlock",
      "value": "*\n * A gamma correction effect.\n *\n * @deprecated Set WebGLRenderer.outputEncoding to sRGBEncoding instead.\n ",
      "start": 171,
      "end": 284,
      "loc": {
        "start": {
          "line": 7,
          "column": 0
        },
        "end": {
          "line": 11,
          "column": 3
        }
      }
    },
    {
      "type": {
        "label": "export",
        "keyword": "export",
        "beforeExpr": false,
        "startsExpr": false,
        "rightAssociative": false,
        "isLoop": false,
        "isAssign": false,
        "prefix": false,
        "postfix": false,
        "binop": null,
        "updateContext": null
      },
      "value": "export",
      "start": 286,
      "end": 292,
      "loc": {
        "start": {
          "line": 13,
          "column": 0
        },
        "end": {
          "line": 13,
          "column": 6
        }
      }
    },
    {
      "type": {
        "label": "class",
        "keyword": "class",
        "beforeExpr": false,
        "startsExpr": false,
        "rightAssociative": false,
        "isLoop": false,
        "isAssign": false,
        "prefix": false,
        "postfix": false,
        "binop": null,
        "updateContext": null
      },
      "value": "class",
      "start": 293,
      "end": 298,
      "loc": {
        "start": {
          "line": 13,
          "column": 7
        },
        "end": {
          "line": 13,
          "column": 12
        }
      }
    },
    {
      "type": {
        "label": "name",
        "beforeExpr": false,
        "startsExpr": true,
        "rightAssociative": false,
        "isLoop": false,
        "isAssign": false,
        "prefix": false,
        "postfix": false,
        "binop": null
      },
      "value": "GammaCorrectionEffect",
      "start": 299,
      "end": 320,
      "loc": {
        "start": {
          "line": 13,
          "column": 13
        },
        "end": {
          "line": 13,
          "column": 34
        }
      }
    },
    {
      "type": {
        "label": "extends",
        "keyword": "extends",
        "beforeExpr": true,
        "startsExpr": false,
        "rightAssociative": false,
        "isLoop": false,
        "isAssign": false,
        "prefix": false,
        "postfix": false,
        "binop": null,
        "updateContext": null
      },
      "value": "extends",
      "start": 321,
      "end": 328,
      "loc": {
        "start": {
          "line": 13,
          "column": 35
        },
        "end": {
          "line": 13,
          "column": 42
        }
      }
    },
    {
      "type": {
        "label": "name",
        "beforeExpr": false,
        "startsExpr": true,
        "rightAssociative": false,
        "isLoop": false,
        "isAssign": false,
        "prefix": false,
        "postfix": false,
        "binop": null
      },
      "value": "Effect",
      "start": 329,
      "end": 335,
      "loc": {
        "start": {
          "line": 13,
          "column": 43
        },
        "end": {
          "line": 13,
          "column": 49
        }
      }
    },
    {
      "type": {
        "label": "{",
        "beforeExpr": true,
        "startsExpr": true,
        "rightAssociative": false,
        "isLoop": false,
        "isAssign": false,
        "prefix": false,
        "postfix": false,
        "binop": null
      },
      "start": 336,
      "end": 337,
      "loc": {
        "start": {
          "line": 13,
          "column": 50
        },
        "end": {
          "line": 13,
          "column": 51
        }
      }
    },
    {
      "type": "CommentBlock",
      "value": "*\n\t * Constructs a new gamma correction effect.\n\t *\n\t * @param {Object} [options] - The options.\n\t * @param {BlendFunction} [options.blendFunction=BlendFunction.SRC] - The blend function of this effect.\n\t * @param {Number} [options.gamma=2.0] - The gamma factor.\n\t ",
      "start": 340,
      "end": 609,
      "loc": {
        "start": {
          "line": 15,
          "column": 1
        },
        "end": {
          "line": 21,
          "column": 4
        }
      }
    },
    {
      "type": {
        "label": "name",
        "beforeExpr": false,
        "startsExpr": true,
        "rightAssociative": false,
        "isLoop": false,
        "isAssign": false,
        "prefix": false,
        "postfix": false,
        "binop": null
      },
      "value": "constructor",
      "start": 612,
      "end": 623,
      "loc": {
        "start": {
          "line": 23,
          "column": 1
        },
        "end": {
          "line": 23,
          "column": 12
        }
      }
    },
    {
      "type": {
        "label": "(",
        "beforeExpr": true,
        "startsExpr": true,
        "rightAssociative": false,
        "isLoop": false,
        "isAssign": false,
        "prefix": false,
        "postfix": false,
        "binop": null
      },
      "start": 623,
      "end": 624,
      "loc": {
        "start": {
          "line": 23,
          "column": 12
        },
        "end": {
          "line": 23,
          "column": 13
        }
      }
    },
    {
      "type": {
        "label": "{",
        "beforeExpr": true,
        "startsExpr": true,
        "rightAssociative": false,
        "isLoop": false,
        "isAssign": false,
        "prefix": false,
        "postfix": false,
        "binop": null
      },
      "start": 624,
      "end": 625,
      "loc": {
        "start": {
          "line": 23,
          "column": 13
        },
        "end": {
          "line": 23,
          "column": 14
        }
      }
    },
    {
      "type": {
        "label": "name",
        "beforeExpr": false,
        "startsExpr": true,
        "rightAssociative": false,
        "isLoop": false,
        "isAssign": false,
        "prefix": false,
        "postfix": false,
        "binop": null
      },
      "value": "blendFunction",
      "start": 626,
      "end": 639,
      "loc": {
        "start": {
          "line": 23,
          "column": 15
        },
        "end": {
          "line": 23,
          "column": 28
        }
      }
    },
    {
      "type": {
        "label": "=",
        "beforeExpr": true,
        "startsExpr": false,
        "rightAssociative": false,
        "isLoop": false,
        "isAssign": true,
        "prefix": false,
        "postfix": false,
        "binop": null,
        "updateContext": null
      },
      "value": "=",
      "start": 640,
      "end": 641,
      "loc": {
        "start": {
          "line": 23,
          "column": 29
        },
        "end": {
          "line": 23,
          "column": 30
        }
      }
    },
    {
      "type": {
        "label": "name",
        "beforeExpr": false,
        "startsExpr": true,
        "rightAssociative": false,
        "isLoop": false,
        "isAssign": false,
        "prefix": false,
        "postfix": false,
        "binop": null
      },
      "value": "BlendFunction",
      "start": 642,
      "end": 655,
      "loc": {
        "start": {
          "line": 23,
          "column": 31
        },
        "end": {
          "line": 23,
          "column": 44
        }
      }
    },
    {
      "type": {
        "label": ".",
        "beforeExpr": false,
        "startsExpr": false,
        "rightAssociative": false,
        "isLoop": false,
        "isAssign": false,
        "prefix": false,
        "postfix": false,
        "binop": null,
        "updateContext": null
      },
      "start": 655,
      "end": 656,
      "loc": {
        "start": {
          "line": 23,
          "column": 44
        },
        "end": {
          "line": 23,
          "column": 45
        }
      }
    },
    {
      "type": {
        "label": "name",
        "beforeExpr": false,
        "startsExpr": true,
        "rightAssociative": false,
        "isLoop": false,
        "isAssign": false,
        "prefix": false,
        "postfix": false,
        "binop": null
      },
      "value": "SRC",
      "start": 656,
      "end": 659,
      "loc": {
        "start": {
          "line": 23,
          "column": 45
        },
        "end": {
          "line": 23,
          "column": 48
        }
      }
    },
    {
      "type": {
        "label": ",",
        "beforeExpr": true,
        "startsExpr": false,
        "rightAssociative": false,
        "isLoop": false,
        "isAssign": false,
        "prefix": false,
        "postfix": false,
        "binop": null,
        "updateContext": null
      },
      "start": 659,
      "end": 660,
      "loc": {
        "start": {
          "line": 23,
          "column": 48
        },
        "end": {
          "line": 23,
          "column": 49
        }
      }
    },
    {
      "type": {
        "label": "name",
        "beforeExpr": false,
        "startsExpr": true,
        "rightAssociative": false,
        "isLoop": false,
        "isAssign": false,
        "prefix": false,
        "postfix": false,
        "binop": null
      },
      "value": "gamma",
      "start": 661,
      "end": 666,
      "loc": {
        "start": {
          "line": 23,
          "column": 50
        },
        "end": {
          "line": 23,
          "column": 55
        }
      }
    },
    {
      "type": {
        "label": "=",
        "beforeExpr": true,
        "startsExpr": false,
        "rightAssociative": false,
        "isLoop": false,
        "isAssign": true,
        "prefix": false,
        "postfix": false,
        "binop": null,
        "updateContext": null
      },
      "value": "=",
      "start": 667,
      "end": 668,
      "loc": {
        "start": {
          "line": 23,
          "column": 56
        },
        "end": {
          "line": 23,
          "column": 57
        }
      }
    },
    {
      "type": {
        "label": "num",
        "beforeExpr": false,
        "startsExpr": true,
        "rightAssociative": false,
        "isLoop": false,
        "isAssign": false,
        "prefix": false,
        "postfix": false,
        "binop": null,
        "updateContext": null
      },
      "value": 2,
      "start": 669,
      "end": 672,
      "loc": {
        "start": {
          "line": 23,
          "column": 58
        },
        "end": {
          "line": 23,
          "column": 61
        }
      }
    },
    {
      "type": {
        "label": "}",
        "beforeExpr": false,
        "startsExpr": false,
        "rightAssociative": false,
        "isLoop": false,
        "isAssign": false,
        "prefix": false,
        "postfix": false,
        "binop": null
      },
      "start": 673,
      "end": 674,
      "loc": {
        "start": {
          "line": 23,
          "column": 62
        },
        "end": {
          "line": 23,
          "column": 63
        }
      }
    },
    {
      "type": {
        "label": "=",
        "beforeExpr": true,
        "startsExpr": false,
        "rightAssociative": false,
        "isLoop": false,
        "isAssign": true,
        "prefix": false,
        "postfix": false,
        "binop": null,
        "updateContext": null
      },
      "value": "=",
      "start": 675,
      "end": 676,
      "loc": {
        "start": {
          "line": 23,
          "column": 64
        },
        "end": {
          "line": 23,
          "column": 65
        }
      }
    },
    {
      "type": {
        "label": "{",
        "beforeExpr": true,
        "startsExpr": true,
        "rightAssociative": false,
        "isLoop": false,
        "isAssign": false,
        "prefix": false,
        "postfix": false,
        "binop": null
      },
      "start": 677,
      "end": 678,
      "loc": {
        "start": {
          "line": 23,
          "column": 66
        },
        "end": {
          "line": 23,
          "column": 67
        }
      }
    },
    {
      "type": {
        "label": "}",
        "beforeExpr": false,
        "startsExpr": false,
        "rightAssociative": false,
        "isLoop": false,
        "isAssign": false,
        "prefix": false,
        "postfix": false,
        "binop": null
      },
      "start": 678,
      "end": 679,
      "loc": {
        "start": {
          "line": 23,
          "column": 67
        },
        "end": {
          "line": 23,
          "column": 68
        }
      }
    },
    {
      "type": {
        "label": ")",
        "beforeExpr": false,
        "startsExpr": false,
        "rightAssociative": false,
        "isLoop": false,
        "isAssign": false,
        "prefix": false,
        "postfix": false,
        "binop": null
      },
      "start": 679,
      "end": 680,
      "loc": {
        "start": {
          "line": 23,
          "column": 68
        },
        "end": {
          "line": 23,
          "column": 69
        }
      }
    },
    {
      "type": {
        "label": "{",
        "beforeExpr": true,
        "startsExpr": true,
        "rightAssociative": false,
        "isLoop": false,
        "isAssign": false,
        "prefix": false,
        "postfix": false,
        "binop": null
      },
      "start": 681,
      "end": 682,
      "loc": {
        "start": {
          "line": 23,
          "column": 70
        },
        "end": {
          "line": 23,
          "column": 71
        }
      }
    },
    {
      "type": {
        "label": "super",
        "keyword": "super",
        "beforeExpr": false,
        "startsExpr": true,
        "rightAssociative": false,
        "isLoop": false,
        "isAssign": false,
        "prefix": false,
        "postfix": false,
        "binop": null,
        "updateContext": null
      },
      "value": "super",
      "start": 686,
      "end": 691,
      "loc": {
        "start": {
          "line": 25,
          "column": 2
        },
        "end": {
          "line": 25,
          "column": 7
        }
      }
    },
    {
      "type": {
        "label": "(",
        "beforeExpr": true,
        "startsExpr": true,
        "rightAssociative": false,
        "isLoop": false,
        "isAssign": false,
        "prefix": false,
        "postfix": false,
        "binop": null
      },
      "start": 691,
      "end": 692,
      "loc": {
        "start": {
          "line": 25,
          "column": 7
        },
        "end": {
          "line": 25,
          "column": 8
        }
      }
    },
    {
      "type": {
        "label": "string",
        "beforeExpr": false,
        "startsExpr": true,
        "rightAssociative": false,
        "isLoop": false,
        "isAssign": false,
        "prefix": false,
        "postfix": false,
        "binop": null,
        "updateContext": null
      },
      "value": "GammaCorrectionEffect",
      "start": 692,
      "end": 715,
      "loc": {
        "start": {
          "line": 25,
          "column": 8
        },
        "end": {
          "line": 25,
          "column": 31
        }
      }
    },
    {
      "type": {
        "label": ",",
        "beforeExpr": true,
        "startsExpr": false,
        "rightAssociative": false,
        "isLoop": false,
        "isAssign": false,
        "prefix": false,
        "postfix": false,
        "binop": null,
        "updateContext": null
      },
      "start": 715,
      "end": 716,
      "loc": {
        "start": {
          "line": 25,
          "column": 31
        },
        "end": {
          "line": 25,
          "column": 32
        }
      }
    },
    {
      "type": {
        "label": "name",
        "beforeExpr": false,
        "startsExpr": true,
        "rightAssociative": false,
        "isLoop": false,
        "isAssign": false,
        "prefix": false,
        "postfix": false,
        "binop": null
      },
      "value": "fragmentShader",
      "start": 717,
      "end": 731,
      "loc": {
        "start": {
          "line": 25,
          "column": 33
        },
        "end": {
          "line": 25,
          "column": 47
        }
      }
    },
    {
      "type": {
        "label": ",",
        "beforeExpr": true,
        "startsExpr": false,
        "rightAssociative": false,
        "isLoop": false,
        "isAssign": false,
        "prefix": false,
        "postfix": false,
        "binop": null,
        "updateContext": null
      },
      "start": 731,
      "end": 732,
      "loc": {
        "start": {
          "line": 25,
          "column": 47
        },
        "end": {
          "line": 25,
          "column": 48
        }
      }
    },
    {
      "type": {
        "label": "{",
        "beforeExpr": true,
        "startsExpr": true,
        "rightAssociative": false,
        "isLoop": false,
        "isAssign": false,
        "prefix": false,
        "postfix": false,
        "binop": null
      },
      "start": 733,
      "end": 734,
      "loc": {
        "start": {
          "line": 25,
          "column": 49
        },
        "end": {
          "line": 25,
          "column": 50
        }
      }
    },
    {
      "type": {
        "label": "name",
        "beforeExpr": false,
        "startsExpr": true,
        "rightAssociative": false,
        "isLoop": false,
        "isAssign": false,
        "prefix": false,
        "postfix": false,
        "binop": null
      },
      "value": "blendFunction",
      "start": 738,
      "end": 751,
      "loc": {
        "start": {
          "line": 26,
          "column": 3
        },
        "end": {
          "line": 26,
          "column": 16
        }
      }
    },
    {
      "type": {
        "label": ",",
        "beforeExpr": true,
        "startsExpr": false,
        "rightAssociative": false,
        "isLoop": false,
        "isAssign": false,
        "prefix": false,
        "postfix": false,
        "binop": null,
        "updateContext": null
      },
      "start": 751,
      "end": 752,
      "loc": {
        "start": {
          "line": 26,
          "column": 16
        },
        "end": {
          "line": 26,
          "column": 17
        }
      }
    },
    {
      "type": {
        "label": "name",
        "beforeExpr": false,
        "startsExpr": true,
        "rightAssociative": false,
        "isLoop": false,
        "isAssign": false,
        "prefix": false,
        "postfix": false,
        "binop": null
      },
      "value": "uniforms",
      "start": 756,
      "end": 764,
      "loc": {
        "start": {
          "line": 27,
          "column": 3
        },
        "end": {
          "line": 27,
          "column": 11
        }
      }
    },
    {
      "type": {
        "label": ":",
        "beforeExpr": true,
        "startsExpr": false,
        "rightAssociative": false,
        "isLoop": false,
        "isAssign": false,
        "prefix": false,
        "postfix": false,
        "binop": null,
        "updateContext": null
      },
      "start": 764,
      "end": 765,
      "loc": {
        "start": {
          "line": 27,
          "column": 11
        },
        "end": {
          "line": 27,
          "column": 12
        }
      }
    },
    {
      "type": {
        "label": "new",
        "keyword": "new",
        "beforeExpr": true,
        "startsExpr": true,
        "rightAssociative": false,
        "isLoop": false,
        "isAssign": false,
        "prefix": false,
        "postfix": false,
        "binop": null,
        "updateContext": null
      },
      "value": "new",
      "start": 766,
      "end": 769,
      "loc": {
        "start": {
          "line": 27,
          "column": 13
        },
        "end": {
          "line": 27,
          "column": 16
        }
      }
    },
    {
      "type": {
        "label": "name",
        "beforeExpr": false,
        "startsExpr": true,
        "rightAssociative": false,
        "isLoop": false,
        "isAssign": false,
        "prefix": false,
        "postfix": false,
        "binop": null
      },
      "value": "Map",
      "start": 770,
      "end": 773,
      "loc": {
        "start": {
          "line": 27,
          "column": 17
        },
        "end": {
          "line": 27,
          "column": 20
        }
      }
    },
    {
      "type": {
        "label": "(",
        "beforeExpr": true,
        "startsExpr": true,
        "rightAssociative": false,
        "isLoop": false,
        "isAssign": false,
        "prefix": false,
        "postfix": false,
        "binop": null
      },
      "start": 773,
      "end": 774,
      "loc": {
        "start": {
          "line": 27,
          "column": 20
        },
        "end": {
          "line": 27,
          "column": 21
        }
      }
    },
    {
      "type": {
        "label": "[",
        "beforeExpr": true,
        "startsExpr": true,
        "rightAssociative": false,
        "isLoop": false,
        "isAssign": false,
        "prefix": false,
        "postfix": false,
        "binop": null,
        "updateContext": null
      },
      "start": 774,
      "end": 775,
      "loc": {
        "start": {
          "line": 27,
          "column": 21
        },
        "end": {
          "line": 27,
          "column": 22
        }
      }
    },
    {
      "type": {
        "label": "[",
        "beforeExpr": true,
        "startsExpr": true,
        "rightAssociative": false,
        "isLoop": false,
        "isAssign": false,
        "prefix": false,
        "postfix": false,
        "binop": null,
        "updateContext": null
      },
      "start": 780,
      "end": 781,
      "loc": {
        "start": {
          "line": 28,
          "column": 4
        },
        "end": {
          "line": 28,
          "column": 5
        }
      }
    },
    {
      "type": {
        "label": "string",
        "beforeExpr": false,
        "startsExpr": true,
        "rightAssociative": false,
        "isLoop": false,
        "isAssign": false,
        "prefix": false,
        "postfix": false,
        "binop": null,
        "updateContext": null
      },
      "value": "gamma",
      "start": 781,
      "end": 788,
      "loc": {
        "start": {
          "line": 28,
          "column": 5
        },
        "end": {
          "line": 28,
          "column": 12
        }
      }
    },
    {
      "type": {
        "label": ",",
        "beforeExpr": true,
        "startsExpr": false,
        "rightAssociative": false,
        "isLoop": false,
        "isAssign": false,
        "prefix": false,
        "postfix": false,
        "binop": null,
        "updateContext": null
      },
      "start": 788,
      "end": 789,
      "loc": {
        "start": {
          "line": 28,
          "column": 12
        },
        "end": {
          "line": 28,
          "column": 13
        }
      }
    },
    {
      "type": {
        "label": "new",
        "keyword": "new",
        "beforeExpr": true,
        "startsExpr": true,
        "rightAssociative": false,
        "isLoop": false,
        "isAssign": false,
        "prefix": false,
        "postfix": false,
        "binop": null,
        "updateContext": null
      },
      "value": "new",
      "start": 790,
      "end": 793,
      "loc": {
        "start": {
          "line": 28,
          "column": 14
        },
        "end": {
          "line": 28,
          "column": 17
        }
      }
    },
    {
      "type": {
        "label": "name",
        "beforeExpr": false,
        "startsExpr": true,
        "rightAssociative": false,
        "isLoop": false,
        "isAssign": false,
        "prefix": false,
        "postfix": false,
        "binop": null
      },
      "value": "Uniform",
      "start": 794,
      "end": 801,
      "loc": {
        "start": {
          "line": 28,
          "column": 18
        },
        "end": {
          "line": 28,
          "column": 25
        }
      }
    },
    {
      "type": {
        "label": "(",
        "beforeExpr": true,
        "startsExpr": true,
        "rightAssociative": false,
        "isLoop": false,
        "isAssign": false,
        "prefix": false,
        "postfix": false,
        "binop": null
      },
      "start": 801,
      "end": 802,
      "loc": {
        "start": {
          "line": 28,
          "column": 25
        },
        "end": {
          "line": 28,
          "column": 26
        }
      }
    },
    {
      "type": {
        "label": "name",
        "beforeExpr": false,
        "startsExpr": true,
        "rightAssociative": false,
        "isLoop": false,
        "isAssign": false,
        "prefix": false,
        "postfix": false,
        "binop": null
      },
      "value": "gamma",
      "start": 802,
      "end": 807,
      "loc": {
        "start": {
          "line": 28,
          "column": 26
        },
        "end": {
          "line": 28,
          "column": 31
        }
      }
    },
    {
      "type": {
        "label": ")",
        "beforeExpr": false,
        "startsExpr": false,
        "rightAssociative": false,
        "isLoop": false,
        "isAssign": false,
        "prefix": false,
        "postfix": false,
        "binop": null
      },
      "start": 807,
      "end": 808,
      "loc": {
        "start": {
          "line": 28,
          "column": 31
        },
        "end": {
          "line": 28,
          "column": 32
        }
      }
    },
    {
      "type": {
        "label": "]",
        "beforeExpr": false,
        "startsExpr": false,
        "rightAssociative": false,
        "isLoop": false,
        "isAssign": false,
        "prefix": false,
        "postfix": false,
        "binop": null,
        "updateContext": null
      },
      "start": 808,
      "end": 809,
      "loc": {
        "start": {
          "line": 28,
          "column": 32
        },
        "end": {
          "line": 28,
          "column": 33
        }
      }
    },
    {
      "type": {
        "label": "]",
        "beforeExpr": false,
        "startsExpr": false,
        "rightAssociative": false,
        "isLoop": false,
        "isAssign": false,
        "prefix": false,
        "postfix": false,
        "binop": null,
        "updateContext": null
      },
      "start": 813,
      "end": 814,
      "loc": {
        "start": {
          "line": 29,
          "column": 3
        },
        "end": {
          "line": 29,
          "column": 4
        }
      }
    },
    {
      "type": {
        "label": ")",
        "beforeExpr": false,
        "startsExpr": false,
        "rightAssociative": false,
        "isLoop": false,
        "isAssign": false,
        "prefix": false,
        "postfix": false,
        "binop": null
      },
      "start": 814,
      "end": 815,
      "loc": {
        "start": {
          "line": 29,
          "column": 4
        },
        "end": {
          "line": 29,
          "column": 5
        }
      }
    },
    {
      "type": {
        "label": "}",
        "beforeExpr": false,
        "startsExpr": false,
        "rightAssociative": false,
        "isLoop": false,
        "isAssign": false,
        "prefix": false,
        "postfix": false,
        "binop": null
      },
      "start": 818,
      "end": 819,
      "loc": {
        "start": {
          "line": 30,
          "column": 2
        },
        "end": {
          "line": 30,
          "column": 3
        }
      }
    },
    {
      "type": {
        "label": ")",
        "beforeExpr": false,
        "startsExpr": false,
        "rightAssociative": false,
        "isLoop": false,
        "isAssign": false,
        "prefix": false,
        "postfix": false,
        "binop": null
      },
      "start": 819,
      "end": 820,
      "loc": {
        "start": {
          "line": 30,
          "column": 3
        },
        "end": {
          "line": 30,
          "column": 4
        }
      }
    },
    {
      "type": {
        "label": ";",
        "beforeExpr": true,
        "startsExpr": false,
        "rightAssociative": false,
        "isLoop": false,
        "isAssign": false,
        "prefix": false,
        "postfix": false,
        "binop": null,
        "updateContext": null
      },
      "start": 820,
      "end": 821,
      "loc": {
        "start": {
          "line": 30,
          "column": 4
        },
        "end": {
          "line": 30,
          "column": 5
        }
      }
    },
    {
      "type": {
        "label": "}",
        "beforeExpr": false,
        "startsExpr": false,
        "rightAssociative": false,
        "isLoop": false,
        "isAssign": false,
        "prefix": false,
        "postfix": false,
        "binop": null
      },
      "start": 824,
      "end": 825,
      "loc": {
        "start": {
          "line": 32,
          "column": 1
        },
        "end": {
          "line": 32,
          "column": 2
        }
      }
    },
    {
      "type": {
        "label": "}",
        "beforeExpr": false,
        "startsExpr": false,
        "rightAssociative": false,
        "isLoop": false,
        "isAssign": false,
        "prefix": false,
        "postfix": false,
        "binop": null
      },
      "start": 827,
      "end": 828,
      "loc": {
        "start": {
          "line": 34,
          "column": 0
        },
        "end": {
          "line": 34,
          "column": 1
        }
      }
    },
    {
      "type": {
        "label": "eof",
        "beforeExpr": false,
        "startsExpr": false,
        "rightAssociative": false,
        "isLoop": false,
        "isAssign": false,
        "prefix": false,
        "postfix": false,
        "binop": null,
        "updateContext": null
      },
      "start": 829,
      "end": 829,
      "loc": {
        "start": {
          "line": 35,
          "column": 0
        },
        "end": {
          "line": 35,
          "column": 0
        }
      }
    }
  ]
}